bowtie/__init__.py
bowtie/__main__.py
bowtie/_benchmarks.py
bowtie/_cli.py
bowtie/_commands.py
bowtie/_connectables.py
bowtie/_containers.py
bowtie/_core.py
bowtie/_direct_connectable.py
bowtie/_registry.py
bowtie/_report.py
bowtie/_smoke.py
bowtie/_suite.py
bowtie/exceptions.py
bowtie/hypothesis.py
bowtie/py.typed
bowtie/benchmarks/__init__.py
bowtie/benchmarks/draft2020_metaschema.py
bowtie/benchmarks/nested_schemas.py
bowtie/benchmarks/openapi_spec_schema.json
bowtie/benchmarks/useless_keywords.py
bowtie/benchmarks/keywords/additionalProperties.py
bowtie/benchmarks/keywords/contains.py
bowtie/benchmarks/keywords/enum.py
bowtie/benchmarks/keywords/items.py
bowtie/benchmarks/keywords/maxContains.py
bowtie/benchmarks/keywords/maxItems.py
bowtie/benchmarks/keywords/maxLength.py
bowtie/benchmarks/keywords/maxProperties.py
bowtie/benchmarks/keywords/minContains.py
bowtie/benchmarks/keywords/minItems.py
bowtie/benchmarks/keywords/minLength.py
bowtie/benchmarks/keywords/minProperties.py
bowtie/benchmarks/keywords/pattern.py
bowtie/benchmarks/keywords/patternProperties.py
bowtie/benchmarks/keywords/propertyNames.py
bowtie/benchmarks/keywords/required.py
bowtie/benchmarks/keywords/type.py
bowtie/benchmarks/keywords/uniqueItems.py
bowtie/schemas/benchmark_report.json
bowtie/schemas/benchmarks.json
bowtie/schemas/connectables.json
bowtie/schemas/implementation-matrix-versions.json
bowtie/schemas/report.json
bowtie/schemas/api/v1/json-schema-org/implementations.json
bowtie/schemas/cli/filter-implementations.json
bowtie/schemas/cli/info.json
bowtie/schemas/cli/smoke.json
bowtie/schemas/cli/statistics.json
bowtie/schemas/cli/summary.json
bowtie/schemas/cli/trend.json
bowtie/schemas/io/v1.json
bowtie/schemas/io/commands/dialect.json
bowtie/schemas/io/commands/run.json
bowtie/schemas/io/commands/start.json
bowtie/schemas/io/commands/stop.json
bowtie/schemas/models/dialect.json
bowtie/schemas/models/group.json
bowtie/schemas/models/implementation-id.json
bowtie_json_schema-2025.12.3.dist-info/METADATA
bowtie_json_schema-2025.12.3.dist-info/WHEEL
bowtie_json_schema-2025.12.3.dist-info/entry_points.txt
bowtie_json_schema-2025.12.3.dist-info/licenses/LICENSE
bowtie_json_schema-2025.12.3.dist-info/RECORD
