Metadata-Version: 2.4
Name: bowtie-json-schema
Version: 2025.12.3
Summary: A meta-validator for the JSON Schema specification.
Project-URL: Documentation, https://docs.bowtie.report/
Project-URL: Homepage, https://bowtie.report/
Project-URL: Issues, https://github.com/bowtie-json-schema/bowtie/issues/
Project-URL: Funding, https://github.com/sponsors/Julian
Project-URL: Source, https://github.com/bowtie-json-schema/bowtie
Author-email: Julian Berman <Julian+bowtie@GrayVines.com>
License-Expression: MIT
License-File: LICENSE
Keywords: data validation,json,json schema,jsonschema,validation
Classifier: Development Status :: 4 - Beta
Classifier: Intended Audience :: Developers
Classifier: Operating System :: OS Independent
Classifier: Programming Language :: Python
Classifier: Programming Language :: Python :: 3
Classifier: Programming Language :: Python :: 3.13
Classifier: Programming Language :: Python :: 3.14
Classifier: Programming Language :: Python :: Implementation :: CPython
Classifier: Programming Language :: Python :: Implementation :: PyPy
Classifier: Topic :: File Formats :: JSON :: JSON Schema
Requires-Python: >=3.13
Requires-Dist: aiodocker
Requires-Dist: attrs>=22.2.0
Requires-Dist: diagnostic
Requires-Dist: github3-py
Requires-Dist: httpx
Requires-Dist: inflect
Requires-Dist: jsonschema-lexer
Requires-Dist: jsonschema>=4.19.0
Requires-Dist: pyperf
Requires-Dist: referencing-loaders>=2024.5.2
Requires-Dist: referencing>=0.31.0
Requires-Dist: rich
Requires-Dist: rich-click<1.9.5,>=1.8.0
Requires-Dist: rpds-py>=0.18.0
Requires-Dist: structlog
Requires-Dist: url-py>=0.11.3
Provides-Extra: strategies
Requires-Dist: hypothesis>=6.92.1; extra == 'strategies'
